apifunc/__init__.py
apifunc/_version.py
apifunc/apifunc.py
apifunc/cli.py
apifunc/new.py
apifunc-0.1.2.dist-info/licenses/LICENSE
apifunc-0.1.2.dist-info/METADATA
apifunc-0.1.2.dist-info/WHEEL
apifunc-0.1.2.dist-info/entry_points.txt
apifunc-0.1.2.dist-info/top_level.txt
apifunc-0.1.2.dist-info/RECORD
