Metadata-Version: 2.4
Name: apifunc
Version: 0.1.2
Summary: Protocol Interface Functions
Home-page: https://github.com/apifunc/python
Author: apifunc Team
Author-email: info@apifunc.com
License: Apache-2.0
Classifier: Development Status :: 4 - Beta
Classifier: Intended Audience :: Developers
Classifier: License :: OSI Approved :: Apache Software License
Classifier: Programming Language :: Python :: 3
Classifier: Programming Language :: Python :: 3.8
Classifier: Programming Language :: Python :: 3.9
Classifier: Programming Language :: Python :: 3.10
Classifier: Topic :: Software Development :: Libraries :: Python Modules
Requires-Python: >=3.11
License-File: LICENSE
Requires-Dist: aiohttp>=3.8.0
Requires-Dist: websockets>=10.0
Requires-Dist: typing-extensions>=4.0.0
Requires-Dist: redis>=4.0.0
Requires-Dist: paho-mqtt>=1.6.0
Requires-Dist: flask>=2.3.0
Requires-Dist: requests>=2.31.0
Requires-Dist: click>=8.1.0
Requires-Dist: colorama>=0.4.6
Requires-Dist: typing-extensions>=4.9.0
Requires-Dist: pyyaml>=6.0.1
Requires-Dist: fastapi>=0.110.0
Requires-Dist: uvicorn>=0.27.0
Requires-Dist: grpcio>=1.62.0
Requires-Dist: grpcio-tools>=1.62.0
Provides-Extra: full
Requires-Dist: grpcio>=1.40.0; extra == "full"
Requires-Dist: paho-mqtt>=1.6.1; extra == "full"
Requires-Dist: pyzmq>=22.2.1; extra == "full"
Requires-Dist: redis>=4.0.2; extra == "full"
Requires-Dist: pika>=1.2.0; extra == "full"
Requires-Dist: graphql-core>=3.2.0; extra == "full"
Requires-Dist: schedule>=1.1.0; extra == "full"
Provides-Extra: dev
Requires-Dist: pytest>=6.2.5; extra == "dev"
Requires-Dist: pytest-cov>=2.12.1; extra == "dev"
Requires-Dist: black>=21.8b0; extra == "dev"
Requires-Dist: isort>=5.9.3; extra == "dev"
Requires-Dist: flake8>=3.9.2; extra == "dev"
Requires-Dist: mypy>=0.910; extra == "dev"
Dynamic: author
Dynamic: author-email
Dynamic: classifier
Dynamic: description
Dynamic: description-content-type
Dynamic: home-page
Dynamic: license-file
Dynamic: provides-extra
Dynamic: requires-dist
Dynamic: requires-python
Dynamic: summary
